mucket
