Metadata-Version: 1.0
Name: mucket
Version: 0.1.0
Summary: Mock whole S3 buckets
Home-page: https://github.com/plain-vanilla-games/mucket
Author: Jökull Sólberg Auðunsson
Author-email: jokull@solberg.is
License: See LICENSE.
Platform: UNKNOWN
